LICENSE
MANIFEST.in
README.md
TODO.txt
setup.py
bin/gtest_gui
gtest_gui/__init__.py
gtest_gui/__main__.py
gtest_gui/bisect.py
gtest_gui/config_db.py
gtest_gui/dlg_browser.py
gtest_gui/dlg_config.py
gtest_gui/dlg_debug.py
gtest_gui/dlg_font_sel.py
gtest_gui/dlg_help.py
gtest_gui/dlg_job_list.py
gtest_gui/dlg_main.py
gtest_gui/dlg_tc_list.py
gtest_gui/fcntl.py
gtest_gui/filter_expr.py
gtest_gui/gtest_ctrl.py
gtest_gui/gtest_list_tests.py
gtest_gui/gtest_sharding.py
gtest_gui/help_db.py
gtest_gui/main.py
gtest_gui/test_db.py
gtest_gui/tk_utils.py
gtest_gui/tool_tip_db.py
gtest_gui/trace_db.py
gtest_gui/wid_status_line.py
gtest_gui/wid_test_ctrl.py
gtest_gui/wid_test_log.py
gtest_gui/wid_text_sel.py
gtest_gui/wid_tool_tip.py
mote_gtest_gui.egg-info/PKG-INFO
mote_gtest_gui.egg-info/SOURCES.txt
mote_gtest_gui.egg-info/dependency_links.txt
mote_gtest_gui.egg-info/requires.txt
mote_gtest_gui.egg-info/top_level.txt