Metadata-Version: 2.1
Name: mote-gtest-gui
Version: 0.9.0
Summary: Module tester's Gtest GUI is a full-featured graphical user-interface to C++ test applications using the GoogleTest framework.
Home-page: https://github.com/tomzox/gtest_gui
Author: T. Zoerner
Author-email: tomzox@gmail.com
License: UNKNOWN
Keywords: google-test,gtest,testing-tools,test-runners,tkinter,GUI
Platform: posix
Platform: win32
Classifier: Topic :: Software Development :: Testing
Classifier: Development Status :: 5 - Production/Stable
Classifier: License :: OSI Approved :: GNU General Public License v3 (GPLv3)
Classifier: Programming Language :: Python :: 3
Classifier: Operating System :: POSIX
Classifier: Operating System :: Microsoft :: Windows
Classifier: Environment :: X11 Applications
Classifier: Environment :: Win32 (MS Windows)
Classifier: Intended Audience :: Developers
License-File: LICENSE
